Qbited/__init__.py
Qbited/exceptions/__init__.py
Qbited/exceptions/exceptions.py
Qbited/functions/__init__.py
Qbited/functions/function01.py
Qbited/functions/function03.py
Qbited/functions/function04.py
Qbited/functions/function05.py
qbited-0.0.6.dist-info/METADATA
qbited-0.0.6.dist-info/WHEEL
qbited-0.0.6.dist-info/top_level.txt
qbited-0.0.6.dist-info/RECORD
